AlarmTime/AlarmTime.py
AlarmTime/__init__.py
AlarmTime-0.1.4.dist-info/LICENSE.txt
AlarmTime-0.1.4.dist-info/METADATA
AlarmTime-0.1.4.dist-info/WHEEL
AlarmTime-0.1.4.dist-info/top_level.txt
AlarmTime-0.1.4.dist-info/RECORD
