Metadata-Version: 2.1
Name: AlarmTime
Version: 0.1.4
Summary: For calculating time difference from current time to Target time and can detect a time from our natural language
Home-page: https://github.com/shohan98/alarm_time_claculate
Author: Md. Shohanur Rahman
Author-email: dshohan112@gmail.com
License: MIT
Platform: UNKNOWN
Classifier: Programming Language :: Python :: 3
Classifier: Operating System :: OS Independent
Requires-Dist: datetime
Requires-Dist: python-dateutil
Requires-Dist: regex
